MANIFEST.in
README.rst
requirements.txt
setup.py
tictactoe/__init__.py
tictactoe/celery_app.py
tictactoe/config.py
tictactoe/manage.py
tictactoe/settings.py
tictactoe/tictactoe.default.cfg
tictactoe/tictactoe.example.cfg
tictactoe/urls.py
tictactoe/wsgi.py
tictactoe.egg-info/PKG-INFO
tictactoe.egg-info/SOURCES.txt
tictactoe.egg-info/dependency_links.txt
tictactoe.egg-info/entry_points.txt
tictactoe.egg-info/requires.txt
tictactoe.egg-info/top_level.txt
tictactoe/contest/__init__.py
tictactoe/contest/admin.py
tictactoe/contest/fixtures.py
tictactoe/contest/forms.py
tictactoe/contest/logic.py
tictactoe/contest/models.py
tictactoe/contest/tasks.py
tictactoe/contest/tests.py
tictactoe/contest/views.py
tictactoe/contest/migrations/0001_initial.py
tictactoe/contest/migrations/0002_fight.py
tictactoe/contest/migrations/0003_latestentry.py
tictactoe/contest/migrations/0004_auto_20140407_1808.py
tictactoe/contest/migrations/0005_handedoutcaps.py
tictactoe/contest/migrations/0006_remove_handedoutcaps_notes.py
tictactoe/contest/migrations/__init__.py
tictactoe/contest/templatetags/__init__.py
tictactoe/contest/templatetags/contest_extras.py
tictactoe/static/css/board.css
tictactoe/static/css/main.css
tictactoe/static/img/spilgames.png
tictactoe/static/js/fight.js
tictactoe/templates/base.html
tictactoe/templates/main.html
tictactoe/templates/contest/entries.html
tictactoe/templates/contest/entry.html
tictactoe/templates/contest/fight.html
tictactoe/templates/contest/index.html
tictactoe/templates/contest/ranking.html
tictactoe/templates/contest/rules.html
tictactoe/templates/contest/upload.html
tictactoe/templates/contest/who_got_capped.html
tictactoe/templates/registration/login.html
tictactoe/tools/__init__.py
tictactoe/tools/context_processors.py
tictactoe/tools/models.py
tictactoe/tools/testing.py
tictactoe/tools/validators.py
tictactoe/tools/management/__init__.py
tictactoe/tools/management/commands/__init__.py
tictactoe/tools/management/commands/import_users.py