Metadata-Version: 1.1
Name: tictactoe
Version: 0.1.5
Summary: Ultimate Tic-Tac-Toe tictactoe front-end
Home-page: https://github.com/Motiejus/tictactoe
Author: Motiejus Jakštys
Author-email: desired.mta@gmail.com
License: UNKNOWN
Platform: UNKNOWN
Classifier: Development Status :: 2 - Pre-Alpha
Classifier: Programming Language :: Python :: 3
Classifier: Intended Audience :: Education
Classifier: Topic :: Games/Entertainment :: Puzzle Games
Classifier: License :: OSI Approved :: MIT License
